mmcore/__init__.py
mmcore/__main__.py
mmcore/api/__init__.py
mmcore/api/_base.py
mmcore/api/_base_vectors.py
mmcore/api/_typing.py
mmcore/api/base.py
mmcore/api/bbox.py
mmcore/api/color.py
mmcore/api/curves.py
mmcore/api/enums.py
mmcore/api/plane.py
mmcore/api/surface.py
mmcore/api/utils.py
mmcore/api/vectors.py
mmcore/base/__init__.py
mmcore/base/basic.py
mmcore/base/components/__init__.py
mmcore/base/delegate/__init__.py
mmcore/base/descriptors/__init__.py
mmcore/base/ecs/__init__.py
mmcore/base/ecs/cmps/__init__.py
mmcore/base/ecs/components/__init__.py
mmcore/base/ecs/components/spec.json
mmcore/base/ecs/cor/__init__.py
mmcore/base/ecs/entity/__init__.py
mmcore/base/ecs/experimental.py
mmcore/base/ecs/jobs/__init__.py
mmcore/base/ecs/nodes/__init__.py
mmcore/base/ecs/nodes/example.json
mmcore/base/encoders/__init__.py
mmcore/base/experimental.py
mmcore/base/geom/__init__.py
mmcore/base/geom/builder/__init__.py
mmcore/base/geom/materials/__init__.py
mmcore/base/geom/utils.py
mmcore/base/links.py
mmcore/base/manage/__init__.py
mmcore/base/models/__init__.py
mmcore/base/models/_pydantic/__init__.py
mmcore/base/models/gql/__init__.py
mmcore/base/params/__init__.py
mmcore/base/params/asset_example/__init__.py
mmcore/base/params/asset_example/definition.py
mmcore/base/registry/__init__.py
mmcore/base/sharedstate/__init__.py
mmcore/base/sharedstate/socketserver/__init__.py
mmcore/base/table/__init__.py
mmcore/base/tags/__init__.py
mmcore/base/tests/ScriptComponent.json
mmcore/base/tests/test.py
mmcore/base/three/__init__.py
mmcore/base/userdata/__init__.py
mmcore/base/userdata/assets/definitions/controls.json
mmcore/base/userdata/assets/definitions/groupSchema.json
mmcore/base/userdata/assets/definitions/propertiesSchema.json
mmcore/base/userdata/assets/definitions/userdata_schema.json
mmcore/base/userdata/assets/examples/group.json
mmcore/base/userdata/assets/examples/groupSchema.json
mmcore/base/userdata/assets/examples/propertiesSchema.json
mmcore-0.26.0.dist-info/LICENSE
mmcore-0.26.0.dist-info/METADATA
mmcore-0.26.0.dist-info/WHEEL
mmcore-0.26.0.dist-info/RECORD
